pyScatSpheres/__init__.py
pyScatSpheres/displayStandards.py
pyScatSpheres/glob_colors.py
pyScatSpheres/gui_base.py
pyScatSpheres/gui_config.py
pyScatSpheres/hard_sphere_array.py
pyScatSpheres/hard_sphere_arrayApprox.py
pyScatSpheres/hard_sphere_base.py
pyScatSpheres/qdot_sphere_array.py
pyScatSpheres/spherical_utils.py
pyScatSpheres/data/hard_sphere_array2.pkl
pyScatSpheres/data/qdotSphereArray1.pkl
pyScatSpheres/data/qdotSphereArray2_kp0.pkl
pyScatSpheres/data/qdotSphereArray2_kp1.pkl
pyScatSpheres/data/qdotSphereArray2_kp2.pkl
pyScatSpheres-1.0.4.dist-info/LICENSE
pyScatSpheres-1.0.4.dist-info/METADATA
pyScatSpheres-1.0.4.dist-info/WHEEL
pyScatSpheres-1.0.4.dist-info/top_level.txt
pyScatSpheres-1.0.4.dist-info/RECORD
