Metadata-Version: 2.1
Name: pyScatSpheres
Version: 1.0.4
Summary: Scattering of array of spheres, scalar theory
Home-page: https://pypi.org/project/pyScatSpheres
Author: Tarik Ronan Drevon
Author-email: tarik.drevon@stfc.ac.uk
License: UNKNOWN
Project-URL: Documentation, https://pyscatspheres.readthedocs.io/en/latest/
Project-URL: Source, https://github.com/ronandrevon/pyScatSpheres
Keywords: diffraction,spherical,scalar,wave,array
Platform: UNKNOWN
Classifier: Programming Language :: Python :: 3
Classifier: License :: OSI Approved :: MIT License 
Classifier: Operating System :: OS Independent
Requires-Python: >=3.6
Requires-Dist: colorama
Requires-Dist: easygui
Requires-Dist: matplotlib
Requires-Dist: numpy
Requires-Dist: pandas
Requires-Dist: py3nj
Requires-Dist: scipy
